mcp_server_ogp/__init__.py
mcp_server_ogp/__main__.py
mcp_server_ogp/server.py
mcp_server_ogp-0.1.5.dist-info/METADATA
mcp_server_ogp-0.1.5.dist-info/WHEEL
mcp_server_ogp-0.1.5.dist-info/entry_points.txt
mcp_server_ogp-0.1.5.dist-info/RECORD
