Metadata-Version: 2.4
Name: mcp-server-ogp
Version: 0.1.5
Summary: OGP (Open Graph Protocol) information extraction server for Model Context Protocol (MCP)
Author-email: yareyaredesuyo <yareyaredesuyo@gmail.com>
License-Expression: MIT
Keywords: llm,mcp,model-context-protocol,ogp,open-graph,web-scraping
Classifier: Development Status :: 4 - Beta
Classifier: Intended Audience :: Developers
Classifier: License :: OSI Approved :: MIT License
Classifier: Programming Language :: Python :: 3
Classifier: Programming Language :: Python :: 3.10
Classifier: Topic :: Internet :: WWW/HTTP :: Indexing/Search
Classifier: Topic :: Software Development :: Libraries :: Python Modules
Requires-Python: >=3.10
Requires-Dist: beautifulsoup4>=4.12.0
Requires-Dist: fastmcp>=2.5.2
Requires-Dist: httpx>=0.27.0
Requires-Dist: pillow>=10.0.0
Requires-Dist: pydantic>=2.0.0
